localclustering/__init__.py
localclustering/cluster.py
localclustering/demo.py
localclustering/hierarchicalengine.py
localclustering/history.py
localclustering/localengine.py
localclustering/ranking.py
localclustering/definitions/__init__.py
localclustering/definitions/base.py
localclustering/definitions/connectivity.py
localclustering/definitions/util.py
localclustering-0.13.0.dist-info/LICENSE.txt
localclustering-0.13.0.dist-info/METADATA
localclustering-0.13.0.dist-info/WHEEL
localclustering-0.13.0.dist-info/top_level.txt
localclustering-0.13.0.dist-info/RECORD
