Metadata-Version: 2.1
Name: localclustering
Version: 0.13.0
Summary: Python 3 implementation and documentation of the Hermina-Janos local graph clustering algorithm.
Home-page: https://github.com/volfpeter/localclustering
Author: Peter Volf
Author-email: do.volfp@gmail.com
License: AGPLv3+
Keywords: graph network analysis cluster clustering ranking local hierarchical algorithm
Platform: UNKNOWN
Classifier: Development Status :: 5 - Production/Stable
Classifier: Intended Audience :: Developers
Classifier: Intended Audience :: Information Technology
Classifier: Intended Audience :: Science/Research
Classifier: License :: OSI Approved :: GNU General Public License v3 or later (GPLv3+)
Classifier: Natural Language :: English
Classifier: Programming Language :: Python :: 3
Classifier: Topic :: Scientific/Engineering
Classifier: Topic :: Scientific/Engineering :: Information Analysis
Classifier: Topic :: Scientific/Engineering :: Mathematics
Classifier: Topic :: Software Development
Classifier: Topic :: Software Development :: Libraries :: Python Modules
Classifier: Topic :: Utilities
Requires-Python: >=3.5
Requires-Dist: graphscraper (>=0.5)
